{"currentVersionName":"tarifs-1598249252117.json","versionHistory":[{"name":"tarifs-1593688898549.json","syncDateTime":"2020-07-02T11:21:38.639Z","order":1},{"name":"tarifs-1593689104034.json","syncDateTime":"2020-07-02T11:25:04.036Z","order":2},{"name":"tarifs-1594288767075.json","syncDateTime":"2020-07-09T09:59:27.077Z","order":3},{"name":"tarifs-1594288852374.json","syncDateTime":"2020-07-09T10:00:52.377Z","order":4},{"name":"tarifs-1594288936127.json","syncDateTime":"2020-07-09T10:02:16.128Z","order":5},{"name":"tarifs-1594288938777.json","syncDateTime":"2020-07-09T10:02:18.780Z","order":6},{"name":"tarifs-1594296050061.json","syncDateTime":"2020-07-09T12:00:50.064Z","order":7},{"name":"tarifs-1598249247148.json","syncDateTime":"2020-08-24T06:07:27.160Z","order":8},{"name":"tarifs-1598249252117.json","syncDateTime":"2020-08-24T06:07:32.119Z","order":9}]}